ipyannotations/__init__.py
ipyannotations/_doc_utils.py
ipyannotations/_frontend.py
ipyannotations/_version.py
ipyannotations/base.py
ipyannotations/controls/__init__.py
ipyannotations/controls/buttongroup.py
ipyannotations/controls/dropdownbutton.py
ipyannotations/controls/hintedmultiselect.py
ipyannotations/controls/togglebuttongroup.py
ipyannotations/generic/__init__.py
ipyannotations/generic/classification.py
ipyannotations/generic/freetext.py
ipyannotations/generic/generic_mixin.py
ipyannotations/generic/multiclassification.py
ipyannotations/images/__init__.py
ipyannotations/images/annotator.py
ipyannotations/images/classification.py
ipyannotations/images/display.py
ipyannotations/images/freetext.py
ipyannotations/images/canvases/__init__.py
ipyannotations/images/canvases/abstract_canvas.py
ipyannotations/images/canvases/box.py
ipyannotations/images/canvases/color_utils.py
ipyannotations/images/canvases/image_utils.py
ipyannotations/images/canvases/point.py
ipyannotations/images/canvases/polygon.py
ipyannotations/images/canvases/shapes.py
ipyannotations/labextension/package.json
ipyannotations/labextension/static/367.329deb9ca6cd5896d612.js
ipyannotations/labextension/static/480.d68d6bd50a22dd22094a.js
ipyannotations/labextension/static/568.22c5ef1341f488e8bfbe.js
ipyannotations/labextension/static/remoteEntry.da2cfcc6d07f9cc4140f.js
ipyannotations/labextension/static/style.js
ipyannotations/labextension/static/third-party-licenses.json
ipyannotations/nbextension/index.js
ipyannotations/nbextension/index.js.map
ipyannotations/text/__init__.py
ipyannotations/text/classification.py
ipyannotations/text/freetext.py
ipyannotations/text/tagging.py
ipyannotations-0.5.1.data/data/etc/jupyter/nbconfig/notebook.d/ipyannotations.json
ipyannotations-0.5.1.data/data/share/jupyter/labextensions/ipyannotations/install.json
ipyannotations-0.5.1.data/data/share/jupyter/labextensions/ipyannotations/package.json
ipyannotations-0.5.1.dist-info/LICENSE
ipyannotations-0.5.1.dist-info/METADATA
ipyannotations-0.5.1.dist-info/WHEEL
ipyannotations-0.5.1.dist-info/top_level.txt
ipyannotations-0.5.1.dist-info/RECORD
