Metadata-Version: 2.1
Name: ipyannotations
Version: 0.5.1
Summary: Create rich adata annotations in jupyter notebooks.
Home-page: https://github.com/janfreyberg/ipyannotations
Author: Jan Freyberg
Author-email: jan.freyberg@gmail.com
License: MIT
Keywords: Jupyter,Widgets,IPython
Platform: Linux
Platform: Mac OS X
Platform: Windows
Classifier: Intended Audience :: Developers
Classifier: Intended Audience :: Science/Research
Classifier: License :: OSI Approved :: BSD License
Classifier: Programming Language :: Python
Classifier: Programming Language :: Python :: 3
Classifier: Programming Language :: Python :: 3.7
Classifier: Programming Language :: Python :: 3.8
Classifier: Programming Language :: Python :: 3.9
Classifier: Framework :: Jupyter
Requires-Python: >=3.7
License-File: LICENSE
Requires-Dist: ipywidgets (>=7.0.0)
Requires-Dist: ipycanvas (>=0.13.1)
Requires-Dist: palettable
Requires-Dist: Pillow
Requires-Dist: numpy
Requires-Dist: requests
Requires-Dist: ipyevents
Provides-Extra: dev
Requires-Dist: black ; extra == 'dev'
Requires-Dist: flake8 ; extra == 'dev'
Requires-Dist: pre-commit ; extra == 'dev'
Requires-Dist: jupyterlab ; extra == 'dev'
Requires-Dist: notebook ; extra == 'dev'
Requires-Dist: rope ; extra == 'dev'
Requires-Dist: docargs ; extra == 'dev'
Requires-Dist: jupyter-packaging ; extra == 'dev'
Provides-Extra: doc
Requires-Dist: sphinx (>=4.0) ; extra == 'doc'
Requires-Dist: sphinx-rtd-theme ; extra == 'doc'
Requires-Dist: matplotlib ; extra == 'doc'
Requires-Dist: nbsphinx ; extra == 'doc'
Requires-Dist: myst-parser (>=0.12.9) ; extra == 'doc'
Requires-Dist: nbsphinx-link ; extra == 'doc'
Requires-Dist: jupyter-sphinx ; extra == 'doc'
Provides-Extra: examples
Provides-Extra: test
Requires-Dist: pytest (>=6.0) ; extra == 'test'
Requires-Dist: pytest-cov ; extra == 'test'
Requires-Dist: nbval ; extra == 'test'
Requires-Dist: coverage ; extra == 'test'
Requires-Dist: coveralls ; extra == 'test'
Requires-Dist: hypothesis ; extra == 'test'
Requires-Dist: pytest-check ; extra == 'test'
Requires-Dist: mypy (>=0.910) ; extra == 'test'
Requires-Dist: pytest-mock ; extra == 'test'
Requires-Dist: flake8 ; extra == 'test'
Requires-Dist: black ; extra == 'test'
Requires-Dist: types-requests ; extra == 'test'
Requires-Dist: testver (>=0.3.1) ; extra == 'test'
